[{"name":"sql.active_record","payload":{"sql":"SELECT \"items\".* FROM \"items\" WHERE \"items\".\"active\" = ?  ORDER BY \"items\".\"name\" ASC","name":"Item Load","connection_id":70136084574940,"statement_name":null,"binds":[[{"name":"active","cast_type":{"precision":null,"scale":null,"limit":null},"sql_type":"boolean","null":true,"default":"t","default_function":null},"t"]],"line":3,"filename":"/Users/rachelkim/OneDrive/cmu/02 SOPHOMORE/Spring17/67272AppDev/phase/PHASE/app/controllers/home_controller.rb","method":"home"},"time":"2017-07-19T19:56:20.566-04:00","transaction_id":"7bd7972e860844622f65","end":"2017-07-19T19:56:20.566-04:00","children":[],"duration":0.433},{"name":"sql.active_record","payload":{"sql":"SELECT \"items\".* FROM \"items\" WHERE (reorder_level \u003e= inventory_level)  ORDER BY \"items\".\"name\" ASC","name":"Item Load","connection_id":70136084574940,"statement_name":null,"binds":[],"line":4,"filename":"/Users/rachelkim/OneDrive/cmu/02 SOPHOMORE/Spring17/67272AppDev/phase/PHASE/app/controllers/home_controller.rb","method":"home"},"time":"2017-07-19T19:56:20.568-04:00","transaction_id":"7bd7972e860844622f65","end":"2017-07-19T19:56:20.568-04:00","children":[],"duration":0.435},{"name":"sql.active_record","payload":{"sql":"SELECT DISTINCT \"orders\".* FROM \"orders\" INNER JOIN \"order_items\" ON \"order_items\".\"order_id\" = \"orders\".\"id\" WHERE (order_items.shipped_on IS NULL)","name":"Order Load","connection_id":70136084574940,"statement_name":null,"binds":[],"line":5,"filename":"/Users/rachelkim/OneDrive/cmu/02 SOPHOMORE/Spring17/67272AppDev/phase/PHASE/app/controllers/home_controller.rb","method":"home"},"time":"2017-07-19T19:56:20.569-04:00","transaction_id":"7bd7972e860844622f65","end":"2017-07-19T19:56:20.570-04:00","children":[],"duration":0.531},{"name":"render_partial.action_view","payload":{"identifier":"/Users/rachelkim/OneDrive/cmu/02 SOPHOMORE/Spring17/67272AppDev/phase/PHASE/app/views/home/_general_home.html.erb","exception":["ActionView::Template::Error","Missing partial ../items/_list_items with {:locale=\u003e[:en], :formats=\u003e[:html], :variants=\u003e[], :handlers=\u003e[:erb, :builder, :raw, :ruby, :coffee, :jbuilder]}. Searched in:\n  * \"/Users/rachelkim/OneDrive/cmu/02 SOPHOMORE/Spring17/67272AppDev/phase/PHASE/app/views\"\n"]},"time":"2017-07-19T19:56:20.579-04:00","transaction_id":"3854966a1f2870dbbd2d","end":"2017-07-19T19:56:20.584-04:00","children":[],"duration":4.563000000000001},{"name":"render_template.action_view","payload":{"identifier":"/Users/rachelkim/OneDrive/cmu/02 SOPHOMORE/Spring17/67272AppDev/phase/PHASE/app/views/home/home.html.erb","layout":"layouts/application","exception":["ActionView::Template::Error","Missing partial ../items/_list_items with {:locale=\u003e[:en], :formats=\u003e[:html], :variants=\u003e[], :handlers=\u003e[:erb, :builder, :raw, :ruby, :coffee, :jbuilder]}. Searched in:\n  * \"/Users/rachelkim/OneDrive/cmu/02 SOPHOMORE/Spring17/67272AppDev/phase/PHASE/app/views\"\n"]},"time":"2017-07-19T19:56:20.577-04:00","transaction_id":"3854966a1f2870dbbd2d","end":"2017-07-19T19:56:20.584-04:00","children":[],"duration":7.165},{"name":"process_action.action_controller","payload":{"controller":"HomeController","action":"home","params":{"controller":"home","action":"home"},"format":"html","method":"GET","path":"/home","view_runtime":null,"db_runtime":0.7010000000000001,"exception":["ActionView::Template::Error","Missing partial ../items/_list_items with {:locale=\u003e[:en], :formats=\u003e[:html], :variants=\u003e[], :handlers=\u003e[:erb, :builder, :raw, :ruby, :coffee, :jbuilder]}. Searched in:\n  * \"/Users/rachelkim/OneDrive/cmu/02 SOPHOMORE/Spring17/67272AppDev/phase/PHASE/app/views\"\n"],"status":"500"},"time":"2017-07-19T19:56:20.565-04:00","transaction_id":"3854966a1f2870dbbd2d","end":"2017-07-19T19:56:20.585-04:00","children":[],"duration":19.992},{"name":"process_action.action_controller.exception","payload":{"call":"ActionView::Template::Error (Missing partial ../items/_list_items with {:locale=\u003e[:en], :formats=\u003e[:html], :variants=\u003e[], :handlers=\u003e[:erb, :builder, :raw, :ruby, :coffee, :jbuilder]}. Searched in:\n  * \"/Users/rachelkim/OneDrive/cmu/02 SOPHOMORE/Spring17/67272AppDev/phase/PHASE/app/views\"\n)"},"time":0,"transaction_id":null,"end":0,"children":[],"duration":0.0},{"name":"process_action.action_controller.exception","payload":{"call":"app/views/home/_general_home.html.erb:1:in `_app_views_home__general_home_html_erb___2565932387813536720_70136133247380'"},"time":0,"transaction_id":null,"end":0,"children":[],"duration":0.0},{"name":"process_action.action_controller.exception","payload":{"call":"app/views/home/home.html.erb:15:in `_app_views_home_home_html_erb__528846502661770981_70136133430540'"},"time":0,"transaction_id":null,"end":0,"children":[],"duration":0.0}]